[{"name":"林逸軒","email":"Dean835058@hotmail.com","latestUpdate":"2012-02-29 21:52:35","objective":"1.進階的設計表現技法，藉由意象表徵，仿生擬人，情境描繪等方法，探求設計表達的背後的意義。2.設計表現法主要素求是由簡易材料之運用以手繪快速描繪出蘊釀中造形，呈現將來產品形態。3.發表的概念草圖與版面設計規劃技巧，也是本課程的訓練重點。4.本課程以團對合作來執行設計表達。","schedule":"Week01 (2/20) –  粉彩\n課程說明  \n個立方體/長方體 - 透視 /陰影說明\n作業 – \n1. 加入Facebook - 設計表現技法2 | NTUT http://www.facebook.com/groups/327326907309763/\n2. 粉彩 : 3個立方體/長方體(須有背景及陰影) x 3(A2) \n\n Week02 (2/27) –   100年校慶補假 (放假一天)  \n                          \nWeek03 (3/5) –粉彩\n作業檢討\n圓柱/圓錐/圓球 - 透視 /陰影說明\n作業 – \n1. 粉彩 : 1個立方體/長方體+1個圓錐/圓柱+1圓球(須有背景及陰影) x 2(A2)\n\nWeek04 (3/12) –粉彩\n作業檢討\n作業 – \n1. 粉彩/細節變化 : 1個立方體/長方體+1個圓錐/圓柱+1圓球(須有背景及陰影) x 2(A2)\n2. 帶一個產品\n\n\nWeek05 (3/19) –粉彩\n作業檢討\n作業 – \n1. 粉彩 產品正視圖 x 1(A2)\n Week06 (3/26)– 麥克筆 : 灰階\n作業檢討\n麥克筆講解 - 立方體/長方體\n作業 – \n1. 麥克筆/灰階 : 立方體/長方體x 3(A3)\n\nWeek07 (4/2) –麥克筆 : 灰階\n作業檢討\n麥克筆講解 – 圓錐/圓柱/圓球\n作業 – \n1. 麥克筆/灰階 : 圓錐/圓柱/圓球x 3(A3)\n\nWeek08 (4/9) –麥克筆/粉彩 : 彩色\n作業檢討\n麥克筆/粉彩 講解 – 圓錐/圓柱/圓球\n作業 – \n1. 麥克筆/粉彩 (白色背景) : 冰箱x 2(A3)\n2. 麥克筆/粉彩 (有色背景) : 冰箱x 2(A3)\n\n\n\nWeek09 (4/16) – 期中考\n\nWeek10 (4/23) – Photoshop\n作業檢討\nPhotoshop 講解\n作業 – \n1. Photoshop : 冰箱x 4(A3)\n\nWeek11 (4/30) – 麥克筆/粉彩 : 木紋/透明\n作業檢討\n木紋/透明材質講解 \n作業 – \n1. 麥克筆/粉彩 : 木紋產品x 2(A3)\n2. 麥克筆/粉彩 : 透明/壓克力產品x 1(A3)\n2. 麥克筆/粉彩 : 木紋+透明/壓克力產品x 1(A3)\n\nWeek12 (5/7) – 麥克筆/粉彩 : 玻璃\n作業檢討\n玻璃材質講解 \n作業 – \n1. 麥克筆/粉彩 (白色背景) : 玻璃杯x 2(A3)\n2. 麥克筆/粉彩 (有色背景) : 玻璃杯x 2(A3)\n\n\n\nWeek13 (5/14) –麥克筆/粉彩 : 電鍍/不鏽鋼\n作業檢討\n玻璃材質講解 \n作業 – \n1. 麥克筆/粉彩 (白色背景) : 玻璃杯x 2(A3)\n2. 麥克筆/粉彩 (有色背景) : 玻璃杯x 2(A3)\n\n\nWeek14 (5/21) – 水彩+Photoshop\n作業檢討\n水彩+Photoshop講解 \n作業 – \n1. 水彩+Photoshop 產品x 10(A4)\n\nWeek15 (5/28) – 期末作業 – 產品Rendering \n作業檢討\n期末作業講解\n作業 – \n1. 產品Rendering x 1(A3) 線稿 -- 產品透視 + 爆炸圖 + 情境\n\nWeek16 (6/4) –期末作業 – 產品Rendering \n個別作業檢討\n作業 – \n1. 產品Rendering x 1(A3) 線稿 -- 產品透視 + 爆炸圖 + 情境\n\nWeek17 (6/11) –期末作業 發表\n\nWeek18 (6/18) – 期末考 – 繳交作品集","scorePolicy":"作業:80%\n發表:20%","materials":"工具 : 油性鉛筆, COPIC 麥克筆, 粉彩, 固定劑, 思高®牌神奇隱形膠紙, 修稿用的遮蔽膠膜\n參考書: 清水吉治","foreignLanguageTextbooks":false}]
