[{"name":"蕭耀榮","email":"yshiao@ntut.edu.tw","latestUpdate":"2012-02-08 10:05:30","objective":"課程包含模糊控制與灰色系統，培養學生能運用模糊控制與灰色系統之理論於控制系統及車輛系統上，內容包括模糊集合，近似推理理論，解模糊方法，模糊控制器之設計，模糊控制器之應用，.灰色系統，灰預測原理，灰色建模，灰色控制。","schedule":"週次　　上課內容\n1　　LabVIEW programming I\n2　　LabVIEW programming II / Signals and DAQ\n3　　Introduction and Fuzzy logics\n4　　Fuzzy sets / Fuzzy relations term project announce\n5　　Fuzzy graphs and arithmetic Fuzzy rules\n6　　Fuzzy implications\n7　　Fuzzy approximate reasoning\n8　　Fuzzy logic and probability\n9　　midterm Exam　　期中考試\n10　　Fuzzy logic control\n11　　Design of Fuzzy controller\n12　　Design of Fuzzy controller\n13　　Fuzzy model identification\n14　　Introduction of neural network\n15　　theory of neural networkproject\n16　　design of neural network controller\n17　　neural-fuzzy control\n18　　report presentation　　期末考試","scorePolicy":"midterm exam: 25%\nfinal exam:  25%\nproject and presentation: 35%\nhomework 10%\nclass performance: 5%","materials":"textbook: Fuzzy Logic, by John Yen, published by Wiley\nreference book: LabVIEW基礎篇","foreignLanguageTextbooks":false}]
