[{"name":"陳英一","email":"ichen@ntut.edu.tw","latestUpdate":"2012-02-22 23:19:26","objective":"專題演講或書報討論","schedule":"資工系100學年度第2學期碩博士班研究生 專題演講時間表\n週 次　　日 期             演 講 者\n1　　101年2/24 　　謝金雲\n2　　3/3　　         本週停止舉行（期初系務會議）\n3　　3/10　　         中央大學通訊工程系 胡誌麟教授\n4　　3/17　　         資訊策進會陳靜芳博士\n5　　3/24　　         成功大學電機系 李國君教授\n6　　3/31　　         開放源碼社群開發者jserv黃敬群先生\n7　　4/7　　         本週停止舉行(運動會補假一日)\n8　　4/14　　         中山大學電機工程系 許蒼嶺教授\n9　　4/21　　         本週停止舉行　　期中考週\n10　　4/28　　         臺北大學資訊工程系主任 黃俊堯教授\n11　　5/5　　         臺灣科技大學資訊管理系 楊傳凱教授\n12　　5/12　　         東吳大學資訊管理系 郭育政教授\n13　　5/19　　         Auburn University 顧維信教授\n14　　5/26　　         高雄師範大學軟體工程系 葉道明教授\n15　　6/2　　         (邀請中)\n16　　6/9　　         宏周豫新經理\n17　　6/16　　         　　本週停止舉行　　期末考前一週\n18　　6/23　　         本週停止舉行（期末系務會議）","scorePolicy":"　","materials":"　","foreignLanguageTextbooks":false}]
