[{"name":"曾瓊瑤","email":"kamadegi@gmail.com","latestUpdate":"2011-01-06 20:46:53","objective":"國文，是運用本國語言文字，蘊釀於欣賞文藝作品，充實文化內涵，增進思維能力與人文素養的一門課程。\n本課程分為大一上學期2學分，大一下學期2學分。大一上學期的授課內容，以文學名篇為範圍；希望藉此擴建學生深入品味文學趣味的能力，鍛鍊靈活的語文敏感度，默契文學創意，甚而嘗試創作。大一下學期的授課內容，以思想名篇為範圍；希望藉此啟發學生透轍分析各家學說思想，漫步哲人的宇宙天地，跟隨哲人的心路歷程，進而念茲在茲，從容內化，共饗取之不盡用之不竭的先驗與風範。","schedule":"課程大綱\n周次　　　　                 主題\n1　　 課程簡介\n2　　中國哲學的核心關懷—愛、生命實現與自我省思\n3　　在旅行中看世界與自心\n4　　兩代對談與人生扣問—龍應台《親愛的安德烈》、《目送》\n5　　中國哲學對人性的肯定—你怎麼看你自身的潛能\n6　　中國哲學廣大和諧的生命精神\n7　　李家同文選\n8　　人與自然的生命對話—自然寫作\n9　　期中考\n10　　 儒家整全的人性觀\n11　　一體感—中國人生哲學的深刻體會\n12　　覺察之心—個人生命之根本，亦是中華文化之根本\n13　　老莊的智慧—在觀念的相對性中解脫\n14　　相互依存性—萬事萬物之間關係的理解\n15　　從反省死亡看生命意義\n16　　影片欣賞\n17　　思辨能力訓練\n18　　期末考\n\n\n","scorePolicy":"期中考30%\n期末考40%\n平時分數30%","materials":"　","foreignLanguageTextbooks":false}]
