[{"name":"楊重光","email":"ckyang@ntut.edu.tw","latestUpdate":"2017-09-21 16:44:01","objective":"本課程係將個別半導體製造程序視為獨立單元，運用化工單元操作的概念，併同現有半導體產業與未來發展趨勢的分析介紹，再輔以積體電路元件的設計原理，期使具化工背景人員能從製程、設備、元件原理等各方面取得一對半導體製程的整合性觀念。","schedule":"(1)產業概覽\n(2)積體電路基本技術背景\n(3)積體電路設計\n(4)積體電路製造\n(5)內連線RC延遲電路與放大電路\n(6)金屬化製程技術\n(7)平坦化製程技術\n(8)物理氣相沉積與化學氣相沉積技術\n(9)線層/阻障層/種晶層\n(10)金屬填充/金屬互連(0.5~0.18um)\n(11)銅製程整合(0.13um含以上)\n(12)基極/位元線路/電容器\n(13)積體電路製程相關設備","scorePolicy":"30%期中考\n40%期末考\n20%小考\n10%作業","materials":"參考書目:\n\n(1)Semiconductor Devices: Physics and Technology\n3rd Edition \nSimon M. Sze, Ming-Kwei Lee\n\n(2)Semiconductor Manufacturing Technology \nPrentice Hall, 1st edition  (November 19, 2000)\nMichael Quirk\n上課指定講義","foreignLanguageTextbooks":true}]
