[{"name":"李文興","email":"f10911@ntut.edu.tw","latestUpdate":"2007-10-02 16:46:14","objective":"學年：96 　學期：1 　系所名稱：能源與冷凍空調工程系\n科目名稱：中文:計算機概論\n　　　　　英文:Introduction to Computer Science\n任課教授：李文興\n教學目標：計算機系統之基礎觀念及及程式語言撰寫\n授課班級：四冷一\n學分及時數：每週授課計 3 小時\n學期授完計：1 學分\n教科書名：計算機概論；visual basic 6.0程式設計  作者 趙坤茂等；許華青\n出版書局：全華；高立  出版日期 西元2005年 8月\n教材大綱：\n　　本課程的目的是提供學生熟悉電腦程式基本概念、熟悉Visual Basic的發展、學習程式設計、使學生循序漸進地學習各種程式設計的基本觀念,也能夠活用Visual Basic 所提供的各種元件, 設計出實用的視窗介面及有用的程式。主要內容為︰\n1.Visual Basic 概述 2. 程式語言組織與結構3.輸出入與條件敘述 4.選擇控制項及重複結構 5.圖片方塊與計時器 6.內建函數與陣列 7.副程式與程序 8.設計功能表與工具列 9.多表單處理 10.資料庫\n","schedule":"學年：96　 學期：1 　班級：四冷一\n課程名稱：計算機概論　　任課教師：李文興\n週次　　月     日　　時數　　授  課  內  容  要  項　　備        註\n1　　9月19日 　　3　　計算機概論簡介\n2　　9月26日 　　3　　表單與基本指令\n3　　10月3日 　　3　　輸出與輸入\n4　　10月10日 　　3　　條件敘述　　　　　　　(10/10)國慶日(放假一天)\n5　　10月17日 　　3　　條件敘述\n6　　10月24日 　　3　　複習及考試\n7　　10月31日 　　3　　重覆結構(迴圈)\n8　　11月7日 　　3　　重覆結構(迴圈)\n9　　11月14日 　　3　　複習及考試\n10　　11月21日 　　3　　內建函數\n11　　11月28日 　　3　　內建函數\n12　　12月5日 　　3　　陣列\n13　　12月12日 　　3　　陣列\n14　　12月19日 　　3　　複習及考試\n15　　12月26日 　　3　　副程式與程序\n16　　1月2日 　　3　　副程式與程序\n17　　1月9日 　　3　　副程式與程序\n18　　1月16日 　　3　　複習及考試\n","scorePolicy":"評量方式：\n考試成績80%，平時成績：20%\n考試：每月一次，合計四次，每次分數佔學期成績比重 20%\n考試日期：10月24日，11月14日，12月29日，1月16日\n考試方式：上機撰寫程式考試。\n考試時由老師及助教聯合監考，如發現有作弊情事，一律依校規處置。\n平時成績：\n上課認真程度作為評分依據。佔總成績10%。\n作業：每次上課都有作業，佔總成績10%。\n","materials":"參考書籍：\n1.Visual Basic 6入門與應用\n作者：吳權威，王緒溢/著\n出版社：碁峰\n出版日期：2003年05月23日\n語言：繁體中文\n2.Visual Basic 6自學手冊\n作者：Scott Waner/原著\n原文作者：Scott Waner\n譯者：葉涼川\n出版社：美商麥格羅‧希爾\n出版日期：1999年08月25日\n語言：繁體中文\n","foreignLanguageTextbooks":false}]
