[{"name":"汪家昌","email":"jcw@ntut.edu.tw","latestUpdate":"2007-11-19 11:53:58","objective":"包括理論與實驗，由機電所教授共同開課。第一學期探討的內容主要在機電整合技術，側重在機電整合與創新設計相關之專業知識。","schedule":"建立3d 量測之基本觀念及介紹逆向工程、快速原型技術，其中包括了3d 量測之基本觀念建立、了解儀器設備之使用、逆向建模及成型。\n第一週:3d 量測原理\n第二週:ATOS、Z-Corp 400操作示範\n第三週:實務操作\n","scorePolicy":"量測原理小考 30% 報告 30% 成品 40%","materials":"　","foreignLanguageTextbooks":false},{"name":"張合","email":"f10381@ntut.edu.tw","latestUpdate":"2007-10-21 19:38:18","objective":"包括理論與實驗，由機電所教授共同開課。使學生瞭解如何以傳統工具機研發奈米材料之機電相關技術及自行操作設備產出奈米流体。","schedule":"1.奈米技術簡介,奈米材料分類 \n2.奈米材料之結構,奈米材料之物理與化學性質 \n3.奈米材料之製備方法及機電整合相關技術--電弧放電法,高週波感應法及電漿\n  電弧法,奈米材料實作\n","scorePolicy":"上課表現：20％\n實作報告：80％","materials":"自編講羲及powerpoint，奈米科技基礎應用與實作，丁志明著，高立出版。\n","foreignLanguageTextbooks":false},{"name":"蔡定江","email":"tctsai@ntut.edu.tw","latestUpdate":"2007-10-16 12:13:30","objective":"包括理論與實驗，由機電所教授共同開課。第一學期探討的內容主要在機電整合技術，側重在機電整合與創新設計相關之專業知識。　　　　\n1.　　光學干涉理論\n2.　　Moire’ 干涉術及實驗方法\n3.　　斑點干涉術及實驗方法\n4.　　有限元素軟體分析應用於實驗結果之驗證\n","schedule":"週次　　講授內容概要　　教科書章節\n13　　光學干涉物理意義及數學模型實驗項目及有限元素軟體使用簡介　　自編講義\n14　　Moire’干涉術、實驗方法及實作　　自編講義\n15　　斑點干涉術、實驗方法及實作 測驗　　自編講義\n","scorePolicy":"(1)平時表現: 10%, (2)作業(報告): 60%, (3)筆試: 30%。","materials":"助教：吳家昇 製科所研究生二年級\n    Office: 綜科館112-2室\nE-mail: t5568047@ntut.edu.tw\nTel: 27712171 ~ 2039\nOffice hour: 星期五下午1:00-6:00\n","foreignLanguageTextbooks":false},{"name":"鍾清枝","email":"tttsung@ntut.edu.tw","latestUpdate":"2007-11-05 20:29:45","objective":"包括理論與實驗，由機電所教授共同開課。第一學期探討的內容主要在機電整合技術，側重在機電整合與創新設計相關之專業知識。","schedule":"依各指導老師規定。","scorePolicy":"依各指導老師規定。","materials":"依各指導老師規定。","foreignLanguageTextbooks":false}]
