[
  {
    "name": "\n  梁斯寧　教師諮商時間(Office Hours) ",
    "email": "maggieleung@ntut.edu.tw",
    "latestUpdate": "2022-08-13 20:28:42",
    "objective": "This course aims to introduce to students the basic concepts, issues and skills of corpus linguistics, including types of corpora, corpus design and construction, corpus analytical tools and techniques, and methodologies for corpus-based studies. It will discuss the major uses of corpora and the applications of corpus linguistics in English language teaching and learning. In the class, students will read and discuss previous studies, and will be given hands-on activities to use corpora and corpus tools.",
    "schedule": "Tentative course schedule:\n\nWeek 1: Course introduction\nWeek 2: Corpora, corpus tools and corpus analytical techniques\nWeek 3: Workshop: corpus tools (I)\nWeek 4: Workshop: corpus tools (II)\nWeek 5: In-class quiz 1\nWeek 6: Data-Driven Learning\nWeek 7: Extended units of meaning \nWeek 8: Approaches to corpus studies\nWeek 9: Mid-term assessment\nWeek 10: EAP: Guest speaker seminar\nWeek 11: Workshop: corpus tools (III)\nWeek 12: Project consultation\nWeek 13: In-class quiz 2\nWeek 14: ESP: Guest speaker seminar\nWeek 15: Learner corpora\nWeek 16: Oral presentation\nWeek 17: Oral presentation\nWeek 18: Final project",
    "scorePolicy": "Attendance and class participation: 20%\nIn-class quizzes: 30%\nMid-term assessment: 15%\nFinal project: 35%",
    "materials": "To be announced in class",
    "foreignLanguageTextbooks": true,
    "remarks": "By appointment"
  }
]
