[{"name":"吳欣怡","email":"cinewu@mail.ntut.edu.tw","latestUpdate":"2019-05-28 17:32:45","objective":"欲修習這門課的同學，請先了解：這門課不是細數台灣小說改編成電影的歷史，也不是教授小說轉換成電影影像的技巧，課程主要內容是帶著同學來看台灣電影，介紹台灣電影的特色，以及與同學一起討論近年台灣電影與台灣文化之間，彼此交互往返的關係。\n\n在西方電影討論裡，已經注意到看電影時所啟動的五感知覺，如嗅覺、味覺、觸覺、痛覺等，以及可能指涉的文化意義。一個值得注意的現象是，近年台灣電影導演不只是描繪角色的期待、失敗、突破等生命成長故事，而是更注重描繪影像上的感官機能，如邀請觀者，一同閱讀角色的身體特徵，進而理解角色的生命情境，或一同感受銀幕上角色吃東西時的嗅覺與味覺等。\n\n本課程預計帶領同學一同討論《日常對話》（黃惠偵，2016）、《台北抽慉》（林琬玉，2015）、《流浪神狗人》（陳芯宜，2008）、《看不見的台灣》（林明謙，2018）等多部電影。","schedule":"第 01 週：課程介紹\n第 02 週：討論電影《台北抽慉》\n第 03 週：討論電影《台北抽慉》\n第 04 週：小考、討論電影《台北抽慉》\n第 05 週：邀請導演\n第 06 週：邀請導演\n第 07 週：討論電影《日常對話》\n第 08 週：討論電影《流浪神狗人》\n第 09 週：期中報告\n第 10 週：期中報告\n第 11 週：討論電影《看不見的台灣》\n第 12 週：討論電影《看不見的台灣》\n第 13 週：邀請導演\n第 14 週：邀請導演\n第 15 週：期末報告\n第 16 週：期末報告\n第 17 週：休假\n第 18 週：期末回饋","scorePolicy":"＊出席與課程參與度：20%。\n＊課堂小考（預計兩次）：20％。\n＊電影分析（1頁A4、共2次電影分析）：20％。\n＊期中團體報告：20%。\n＊期末團體報告：20%。","materials":"教師自編講義。","foreignLanguageTextbooks":false}]
