[{"name":"洪春凰","email":"hongch@ntut.edu.tw","latestUpdate":"2012-12-26 17:00:15","objective":"本課程希望在一學年中，能使學生對微分及積分有充分的瞭解、培養邏輯推理、拕發思考創造、強化計算演繹並注重應用與作圖，以建立同學未來學習工程數學及相關專業課程之數學基礎，充分達到學以致用的目的。課程內容包括：1.極限與連續，2.導數及其應用，3.不定積分與定積分，4.超越函數及其反函數，5.積分法則，6.不定型與瑕積分，7.定積分的應用，8.空間幾何與向量微積分，9.偏導數，10.重積分。","schedule":"第一週~第三週: 積分技巧\n第四週~第六週: 積分應用\n第七週~第八週: 參數式與極座標\n第九週~第十週: 向量\n第十一週~第十三週: 偏導數\n第十四週~第十六週: 重積分\n第十七週: 向量函數\n第十八週: 期末考","scorePolicy":"1. 平時成績25%，含(點名10%、小考15%)\n2. 助教5%\n3. 期中考35%\n4. 期末考 35%","materials":"1.教科書書名 : 微積分 Calculus   作者 : 林晶璟; 劉國安(新頁圖書)\n2.其它參考的書籍: (1)書名:Calculus (concepts &amp; connections), \n  作者:ROBERT T. SMITH &amp; ROLAND B. MINTON.","foreignLanguageTextbooks":false}]
