[{"name":"張文華","email":"whchang@ntut.edu.tw","latestUpdate":"2013-05-25 11:56:57","objective":"本課程在幫助此課程學習者能夠應用孼費的軟體和網路服務，製作一個基本的商業網站， 以推廣公司業務。","schedule":"週次　　日期　　課程名稱\n1　　2/21　　商業網站設計介紹\n2　　2/28　　不上課\n3　　3/7　　wordpress與商業網站設計-1\n4　　3/14　　wordpress與商業網站設計-2\n5　　3/21　　wordpress與商業網站設計-3\n6　　3/28　　wordpress與商業網站設計-4\n7　　4/4　　不上課\n8　　4/11　　wordpress與商業網站設計-5\n9　　4/18　　wordpress與商業網站設計-6\n10　　4/25　　test\n11　　5/2　　商業部落格設計-1\n12　　5/9　　商業部落格設計-2\n13　　5/16　　商業部落格設計-3\n14　　5/23　　商業部落格設計-4\n15　　5/30　　商業部落格設計-5\n16　　6/6　　商業部落格設計-6\n17　　6/13　　商業部落格設計-7\n18　　6/21　　期末考","scorePolicy":"平時成績：30%\n期中考： 30%\n期末考：40%","materials":"網路孼費資源行銷術：部落格+Facebook+微網誌超Easy\n作者：創意眼資訊\n出版社：博碩\n出版日期：2011年03月18日","foreignLanguageTextbooks":false}]
