[{"name":"許東亞","email":"dongyea@ntut.edu.tw","latestUpdate":"2008-09-18 09:29:15","objective":"先修課程：負責教授同意。半導體元件簡介、電晶體開關電路、數位積體電路及應用、矽控整流子（SCR）、矽控整流子觸發電路、雙向矽控整流器、運算放大器及應用感測器及應用、電動機驅動電路、變頻器電路。","schedule":"第 1  週 用電須知,實驗室安全介紹,上課注意事項,評分標準\n第 2  週 三用電錶使用,電零件子發展導論\n第3,4 週 電阻器,功率計算,瓦特數計算\n第5,6 週 感測器介紹\n第7,8 週 電晶體命名,電晶體增幅回路\n第 9  週 期中考 (停課)\n第 10 週 電晶體功率控制,馬達正反轉控制\n第11,12 週 ON-OFF控制回路,繼電器控制\n第13,14 週 矽控整流器介紹與電路實驗\n第15,16 週 相位控制\n第  17  週 OP放大器介紹與電路實驗\n第 18 週 期末考 (停課)","scorePolicy":"1.平時成績 30% (電路實習,出席,課堂表現)\n2.期中考   30%\n3.期末考  40%","materials":"電子控制學 建興出版社 翻譯作者:浩司\n","foreignLanguageTextbooks":false}]
