[{"name":"于治平","email":"cpyu@ntut.edu.tw","latestUpdate":"2008-09-15 12:00:22","objective":"基本儀器介紹，電子零件之認識。二極體電路：整流、濾波、截波與箝位，稽納二極體。運算放大器：反向與非反向、算術電路、電壓隨耦、積分與微分，儀表放大。電晶體：特性、偏壓、各類放大器組態。放大器的頻率響應，多級與串級放大器，差動放大器，回授放大器，功率放大器，無穩態、單穩態、雙穩態振盪器，訊號產生電路，穩壓電路。","schedule":"第 一 週：分組，課程簡介，儀器使用說明\n第 二 週：儀器使用說明\n第 三 週：二極體特性\n第 四 週：二極體整流與濾波\n第 五 週：稽納二極體之特性與應用\n第 六 週：運算放大器的特性\n第 七 週：運算放大器電路(一)\n第 八 週：運算放大器電路(二)\n第 九 週：期中測驗(實作)\n第 十 週：PSPICE教學(一)\n第十一週：PSPICE教學(二)\n第十二週：雙極性接面電晶體(BJT)的特性\n第十三週：BJT電晶體偏壓電路\n第十四週：BJT電晶體放大器\n第十五週：接面場效電晶體(JFET)的特性\n第十六週：JFET電晶體偏壓電路\n第十七週：JFET電晶體放大器\n第十八週：期末測驗(含筆試與電路銲接)\n","scorePolicy":"實驗成果：30%\n實驗報告：30%\n期中測驗：10%\n期末測驗：20%\n課堂參予態度：10%\n","materials":"電子學實驗(上)(下) 修訂版\n陳瓊興 編著  全華出版\n","foreignLanguageTextbooks":false}]
