[{"name":"簡良翰","email":"lhchien@ntut.edu.tw","latestUpdate":"2019-02-18 18:15:26","objective":"本課程介紹各項節能減碳科技之原理與應用技術。本課程將講授通風與空調系統節能、冷凍系統節能、照明系統節能、能源管理系統、廢熱回收與熱泵系統節能應用，碳排放與碳足跡之計算，減碳原理與技術。","schedule":"週次　　日期　　授 課 內 容 要 項\n1　　2/19, 2/20　　國內外能源使用概況\n2　　2/26, 2/27　　建築能耗分析\n3　　3/5, 3/6　　建築節能\n4　　3/12, 3/13　　通風與空調系統節能\n5　　3/19, 3/20　　熱交換原理\n6　　3/26, 3/27　　廢熱回收與有機朗肯循環\n7　　4/2, 4/3　　有機郎肯循環與廢熱回收\n8　　4/9, 4/10　　熱泵系統節能應用\n9　　4/16, 4/17　　期中考\n10　　4/23, 4/24　　冷凍系統節能\n11　　4/30, 5/1　　冷凍系統節能\n12　　5/7, 5/8　　能源管理系統\n13　　5/14, 5/15　　冷凍系統節能碳排放與碳足跡之計算\n14　　5/21, 5/22　　照明基礎原理\n15　　5/28, 5/29　　照明系統節能\n16　　6/4, 6/6　　燈具與LED照明技術\n17　　6/11, 6/12　　期末考、分組報告\n18　　6/18, 6/9　　分組報告","scorePolicy":"成績計算:期中考(35%)+作業(25%) +課程參與(10%) +分組期末報告 (30%)\n註:1.課程參與成績包括課堂討論之參與度及網路自我評量。\n註:2. 作業須於規定期限內繳交。逾期一週以內者以所得成績之80%計算；逾期一週以上者以零分計算。","materials":"教科書:自編講義。\n參考書:　　\nRefrigeration and Air Conditioning, Wilbert F. Stoecker, 1982, McGraw Hill Higher Education；中譯本：冷凍與空調, 蘇金佳\nRefrigeration and Air Conditioning, 4th Ed., G.F. Hundy, A.R. Trott, T.C. Welch, 2008, Elsevier.\n黃文良 譯，「能源運用及環境」第五版，滄海書局，民國102年。\nHinrichs, R. A., and Kleinbach, M., “Energy: Its Use and the Environment”, 4th Ed. Thomson Learning, Inc.","foreignLanguageTextbooks":false}]
