[{"name":"羅淑娟","email":"sclo@ntut.edu.tw","latestUpdate":"2019-01-24 23:43:42","objective":"使學生瞭解科學研究的特性、研究的類型、測量的程序與工具、資料的收集、資料的分析、撰寫研究計畫的方法，在從事管理問題之研究與探討時，知道如何正確選用適當方法，並取得所需資訊。","schedule":"w1-4, How to read a paper?\na. title\nb. key words, key sentences\nc. paper structures\nw5-8, reading practice\nw9-12, methods and procedures\nw13-16, writing practice\nw17-18 evaluation","scorePolicy":"reading 40%\nwriting 30%\noral presentation 20%\nparticipation 10%","materials":"1. Teitelbaum, Harry. How to Write a Thesis, 5th ed. Thomson Arco, 2003\n\n2. papers and notes","foreignLanguageTextbooks":true}]
