[{"name":"耿慶瑞","email":"cjkeng@ntut.edu.tw","latestUpdate":"2017-02-15 11:12:46","objective":"本課程以哈佛個案教學方法進行，主要以策略管理與營運模式為核心，在每個個案討論當中，同時由策略管理、人力資源管理、組織管理、服務管理領域老師教授。可以讓學生從策略的角度，學習這些管理功能的整合與營運模式，促進團隊互動與學習。","schedule":"2/25 Week 1 :   財務策略(林鳳儀)\n3/ 4 Week 2 :   生產個案(蔡佩芳)\nCASE1: 英特爾: 關於新封裝測試工廠選址的戰略性決策 (A) (哈佛個案 714-C09)\n1.　　你認為這個新廠應該設在哪裡? 為甚麼?\n2.　　如果你代表英特爾，你會要求你所選定新廠址的當地政府給予何種優惠?\n3/11 Week 3 :   行銷策略個案(耿慶瑞)\nCASE2: Tripadvisor (哈佛個案9-515-c01)  \n1.　　為何Tripadvisor會吸引消費者?為何消費者會願意寫口碑\n2.　　飯店對Tripadvisor的想法如何?Tripadvisor如何取得飯店與蕭者的平衡\n3.　　Tripadvisor如何將口碑轉成利潤?與Yelp有何差異?\n4.　　Tripadvisor未來成長的建議?\n3/18 Week 4 :   產業分析 (邱院長)\n\n3/25 Week 5 :   服務個案(蔡佩芳) \nCASE3: 裕隆行(工研院資料庫，請蔡老師幫忙下載)\n1.　　像姿薇這樣的微型企業，是否可以成為策略夥伴? 你認為評估的條件為何?\n2.　　你認為邱總是否應該繼續積極開發客製化的資訊管理系統? 還是應該回到本業精進流程? 為甚麼?\n4/ 1 Week 6 :   財務個案(林鳳儀)\nCASE4: 聚陽實業全球資金管理 (光華個案)\n1.　　聚陽現的資管模式為何？其特點為何？\n2.　　聚陽的資管模式是否適合於現的全球運籌新佈局策，試分析。 \n3.　　聚陽在全球多點佈局下，匯風險為其重要課題之一，如何考慮聚陽的避險操作？可以用何種工具？試舉。 \n4.　　聚陽在經過全球運籌新佈局、e化系統的設以及用銀Factoring服務後，對其營運資的管有何影響？(試分析其營運資需求有無增加或減少) \n5.　　聚陽在經過全球運籌新佈局、e化系統的設以及用銀Factoring服務後，有無調整其庫存現(現+約當現)的管？試分析。\n6.　　聚陽在營運資管上可能遇到的問題？ 你有何建議可以解決這些問題。\n4/ 8 Week 7 :   財務個案 (林鳳儀)\nCASE5: 大同奈陶瓷工業台商海外融資決策 (光華個案)\n1.　　企業進行跨國性投資之動機為何? 進行跨國性投資應考量哪些因素？\n2.　　大同奈公司融資之來源為何？ 其資本結構與財務比率是否恰當？\n3.　　大同奈公司如何決策應以美元或越盾借款？ 若以台幣做為借款貨幣，是否可行？\n4.　　大同奈公司目前正值 2008 年金融海嘯，管理當局應如何因應此金融危機？  \n4/15 Week 8 :   寰騰匯\n4/22 Week 9 :   策略與個案背景分析(耿慶瑞)   \n4/29 Week 10 :   策略個案(耿慶瑞)\nCASE6: Aamzon.com 2016 (哈佛個案9-716-402)\n1.　　你認為Amazon為何一開始選擇賣書?\n2.　　你認為Amazon在2000年網路泡沫化之後，為何能生存並獲利？\n3.　　你認為Amazon在未來最有發展潛力的事業是什麼？\n4.　　未來會有哪家公司會取代Amazon?\n5/6 Week 11 :   營運策略(陳銘崑)\n5/13 Week 12 :   營運個案(陳銘崑)\nCASE7: 萬向集團: 一家中國企業地全球戰略 (哈佛個案9-308-058)\n1.　　萬向全球戰略的關鍵要素是什麼？它們可以被其他中國公司複製嗎？\n2.　　萬向未來的成長有什麼限制，他們面臨什麼樣的風險？ 他們如何減輕這些風險？\n3.　　你對萬向的管理有什麼具體建議？\n5/20 Week 13:   營運個案(陳銘崑)\nCASE8: Nike社群策略 (哈佛個案9-714-C16)\n1.　　評估Nike +生態系統作為公司的基礎。\n2.　　Nike +如何使用Facebook，Twitter和YouTube的數位策略？\n3.　　耐克如何將其數位策略與其社群策略相結合？\n4.　　耐克如何能夠開發如此豐富，整合的社群和數位策略？\n5/27 Week 14 :   領導與策略個案(蔡佩芳) \n[Role Play] Carter Racing\n無指定問題，也無須課前準備\n6/ 3 Week 15 :   補班停課\n6/10 Week 16 :   畢業典禮停課   \n6/17 Week 17 :   產業分析 (邱院長)\n6/24 Week 18 :   策略個案(耿慶瑞)\nCASE9:  Lego(哈佛個案9-616-C03)\n1.　　什麼原因讓LEGO在2004年瀕臨破產邊緣?\n2.　　Knudstorp的轉型策略為何能成功?你認為那些行動是最有效用的?哪些行動是最沒有效用的?\n3.　　你認為樂高應該要發展新的桌游(Board game)產品線嗎?","scorePolicy":"個案課前一頁心得報告: 50%\n課中參與 (思考並參與討論): 50%\n\n作業說明 : 請於個案上課前，針對即將使用的個案，撰寫心得報告並回答指定問題，長度以一頁為限，字體大小為12點，行間距須為1.2~1.5倍行高。","materials":"哈佛個案\n光華管理個案\n共6-8個","foreignLanguageTextbooks":false},{"name":"陳銘崑","email":"mkchen@ntut.edu.tw","latestUpdate":"2016-12-26 14:58:31","objective":"本課程以哈佛個案教學方法進行，主要以策略管理與營運模式為核心，在每個個案討論當中，同時由策略管理、人力資源管理、組織管理、服務管理領域老師教授。可以讓學生從策略的角度，學習這些管理功能的整合與營運模式，學期末並有分組個案競賽，促進團隊互動與學習。","schedule":"Week 1 :   光華基金會 個案一 (陳銘崑)\nWeek 2 :   光華基金會 個案二 (陳銘崑)\nWeek 3 :   光華基金會 個案三 (陳銘崑)","scorePolicy":"個案課前一頁心得報告: 30%\n課中參與 (思考並參與討論): 70%","materials":"光華基金會 個案","foreignLanguageTextbooks":false}]
