[{"name":"謝坤學","email":"hsieh@nespace.com.tw","latestUpdate":"2017-01-30 23:07:31","objective":"整合學科與術科兩大部分，本課程介紹【建築物室內設計】與【建築物室內裝修工程管理】專業技能檢定事宜。參酌最新專業議題並研習歷屆考試題庫，課程加強學／術科模擬考試訓練，期使學校養成教育與設計界之專業需求得以結合。","schedule":"國立台北科技大學 105 學年第 2 學期 室內設計與裝修證照概論 \n教學大綱與進度表 \n \n106\n2 月\n 一  2/22 設 01 課程介紹/教材介紹(開課日)\n\n3 月 \n二  3/1 工 01 工程管理證照概論、學科考古題練習        \n三  3/8 設 02 室內設計基本知識與繪圖技巧          \n四  3/15 工 02 圖說識圖判讀、剖立面圖、施工大樣 圖繪製         \n五  3/22 設 03 室內平面配置與規劃技巧          \n六  3/29 工 03 丈量放樣、室內裝修泥作、木作、 塗裝工程施工 \n\n 4 月\n七  4/5 清明節休假 運動會補假 \n八  4/12 設 04 室內平面設計與繪圖技巧  \n九  4/19 應試技巧與實作演練(一) 期中考試\n十  4/26 設 05 室內立面設計與繪圖技巧  \n\n5 月 \n十一  5/3 工 04 壁布、壁紙、窗簾、地毯、輕隔間及 天花板工程施工作業。金屬工程、玻璃及 壓克力安裝作業。 \n十二  5/10 設 06 施工大樣圖說與繪圖技巧、工程估算 概念 5/12期中撤選截 止 \n十三  5/17 工 05 水電空調、給排水衛生設備、電氣管 線工程施工。 \n十四  5/24 設 07 透視圖說的表現技法；色彩與材質 計劃 \n十五  5/31  工 06 工程管理裝修估算及表格編製填寫\n \n6 月 \n十六  6/7 設 08 透視圖說的表現技法；色彩與材質 計劃\n十七  6/14 工 07 工地安全衛生管理  \n十八  6/21 應試技巧與實作演練(二) 期末考試","scorePolicy":"上課出席 佔 15%\n平時作業 佔 25%\n期中作業 佔 30%\n期末作業 佔 30%","materials":"室內設計\n建築物室內裝修乙級技術士\n室內製圖規範\n施工大樣圖說\n工程估算\n-建築法規\n建築技術規則概論\n主管單位\n-標準局  建材\n-營建署  建築物(消防設施、公共安全檢查)\n-消防署  消防設備、災害預防\n-公共工程委員會、勞委會、建研所、台灣建築中心\n其他\n-衛生署 空氣品質\n-行政院勞工委員會 \n-勞安衛\n-公寓大廈管理條例\n-綠建材","foreignLanguageTextbooks":false}]
