[{"name":"李明哲","email":"aslan_lee@hotmail.com","latestUpdate":"2017-02-20 08:40:50","objective":"行動裝置是當前最熱門的人機介面應用，其中又以Android系統的市佔率最高，但要使用Android應用程式的開發套件(Android Studio)來開發APP，卻要熟悉極重物件導向觀念的Java程式以及先學習 XML語法，這二樣對於要邁入行動應用的初學者來說皆是遙不可及的門檻。為避開此一過高之入門門檻，本課程特別採用由Google推出的App Inventor 2中文版為工具，只要使用瀏覽器，透過拼圖式的開發環境，不用撰寫任何程式碼，就能輕鬆設計出各式各樣、創意有趣的App，歡迎所有想一窺APP設計堂奧的同學們選修。","schedule":"Lec. #          Date            Contents\n1               106/2/21        課程介紹與軟體安裝\n2               106/3/7         APP Android 2 基本教學\n　　　　　　　　第一個APP\n3               106/3/14        基本元件、事件、方法介紹\n　　　　　　　　小鋼琴範例\n4               106/3/21        常用的使用者介面元件\n　　　　　　　　變數宣告與運算式\n　　　　　　　　條件判斷流程控制\n                                溫度轉換範例　　　　　　　　　　　　　　　　\n5               106/3/28        界面布局元件\n                                滑桿元件\n　　　　　　　　版面配置與繪圖元件\n　　　　　　　　小畫家範例\n6               106/4/11        迴圈指令\n                                清單\n　　　　　　　　副程式\n　　　　　　　　加速度感應器\n                                體感抽籤範例\n7               106/4/18        音訊播放器\n                                圖片元件\n　　　　　　　　計時器元件\n　　　　　　　　元件清單\n　　　　　　　　骰子遊戲範例\n8               106/4/25        期中報告(書面+上台)\n9               106/5/2         Web元件\n                                語音轉換文字元件\n　　　　　　　　天氣查詢系統\n　　　　　　　　電影院資訊查詢\n　　　　　　　　翻譯機\n10              106/5/9         複選方塊元件\n                                對話框元件\n　　　　　　　　被劃動元件\n　　　　　　　　文字轉語音Web服務\n　　　　　　　　電子有聲書\n11              106/5/16        微資料庫元件\n                                社交應用元件\n　　　　　　　　activity啟動器元件\n　　　　　　　　通訊錄範例\n12              106/5/23        位置感測器元件\n                                Web瀏覽器元件\n　　　　　　　　Google map地圖定位\n13              106/6/6         QRcode製做\n                                景點定位資訊\n　　　　　　　　條碼掃描器元件\n　　　　　　　　台北101行動導覽\n14              106/6/13        多重畫面應用\n                                方向感測器元件\n                                動畫元件\n                                氣球遊戲\n                                水平儀　　　　　　　　　　　　　　　　\n15              106/6/20        期末報告(書面+上台)","scorePolicy":"作業 ─ 20%\n課堂表現 ─ 20%\n期中報告 ─ 30% \n期末報告 ─ 30%","materials":"(1) App Inventor2 開發 Android App範例教本  蔡宜坦著  旗標出版社\n(2) Android系統智慧手機1隻","foreignLanguageTextbooks":false}]
