[{"name":"尹世洵","email":"shihhsun@ntut.edu.tw","latestUpdate":"2021-03-22 13:48:38","objective":"以結構工程、大地工程、防災科學、運輸交通、營建管理、營建材料及營建技術為專題討論主題之主要範疇。\nSeminar\nSpecial subject discussion of structure engineering , geography engineering pretecting calamity science, transportation, construction management , construction material and construction technique.","schedule":"每周主題於土木館1F公布","scorePolicy":"出席率與書面心得","materials":"無","foreignLanguageTextbooks":false},{"name":"張國楨","email":"epidote@ntut.edu.tw","latestUpdate":"2021-03-23 22:18:13","objective":"以結構工程、大地工程、防災科學、運輸交通、營建管理、營建材料及營建技術為專題討論主題之主要範疇。\nSeminar\nSpecial subject discussion of structure engineering , geography engineering pretecting calamity science, transportation, construction management , construction material and construction technique.","schedule":"各周內容視邀請之講者而有所不同","scorePolicy":"出席及專題演講之心得報告","materials":"使用教材、參考書目或其他 ：受邀演講者提供演講主題簡報檔、學生提供畢業論文簡報檔","foreignLanguageTextbooks":false}]
