[
  {
    "name": "邱品逢",
    "email": "e2345675@gm.nkhs.tp.edu.tw",
    "latestUpdate": "2023-09-15 14:58:47",
    "objective": "進階冰水主機實習、進階冷凍工程實習、進階中央空調系統實習、空調設備工程品質管理實務、進階空調工程實習。\nAdvanced practices and experiments of water chiller unit, refrigeration engineering, central air conditioning system, quality control of air conditioning facilities, and air conditioning engineering.",
    "schedule": "第一週單元主題冷凍空調基礎原理概論\n第二週單元主題空調性質圖應用實務\n第三週單元主題小型空調系統實務 - 分離式空調安裝實務\n第四週單元主題小型冷凍系統統系處理實務\n第五週單元主題冷凍空調冰熱水系統暨節能設備管理實務\n第六週單元主題商用空調系統 - 箱型冷氣機實務\n第七週單元主題商用空調系統 - 箱型冷氣機性能量測實務\n第八週單元主題中央空調啟動控制電路實務 (部分繞組與 YD 降壓啟動控制)\n第九週期中考\n第十週單元主題中央空系統自動控制與檢測 (故障排除) 技術\n第十一週單元主題多段壓壓縮製冷技術實務\n第十二週單元主題儲冰式空調系統實務\n第十三週單元主題熱泵空調系統實務\n第十四週單元主題吸收式空調系統\n第十五週各組主題設備實務操作說明 1\n第十六週單元主題設備實務操作說明 2\n第十七週單元自主交流學習\n第十八週期末考\n※課程進度與作業要求將視學生學習情況適度調整。",
    "scorePolicy": "1、期中各組報告 30%\n2、期未教學評量 30%\n3、平時考查與作業 40%\n※ 評量項目與配分將視學生學習情況適度調整。",
    "materials": "參考書目冷凍空調實務全華李居芳\n自編教教 PPT\n自編講議",
    "consultation": "1、E-MAIL  :e2345675@gm.nkhs.tp.edu.tw2、tel 02-27825432#14073、line 群組",
    "remarks": "1、Clean Water and Sanitation2、Affordable and Clean Energy",
    "foreignLanguageTextbooks": false
  }
]
