[
  {
    "name": "李凱雄",
    "email": "jordan@wda.gov.tw",
    "latestUpdate": "2023-05-29 16:52:51",
    "objective": "學生與老師討論後，擬定專題製作的題目，在老師的個別指導下，進行研究操作，並將研究結果寫成報告。",
    "schedule": "1. 汽車引擎\n2. 汽車底盤\n3. 汽車電系\n4. 汽車板金\n5. 汽車塗裝",
    "scorePolicy": "1. 研究操作 30%\n2. 定期討論 30%\n3. 作業報告 40%",
    "materials": "自編教材",
    "consultation": "李凱雄老師 e-mail:jordan@wda.gov.tw",
    "remarks": "(https://oaa.ntut.edu.tw/p/404-1008-98622.php?Lang=zh-tw)",
    "foreignLanguageTextbooks": false
  },
  {
    "name": "陳志鏗",
    "email": "ckchen0618@gmail.com",
    "latestUpdate": "2023-05-25 15:31:55",
    "objective": "先修課程：負責教授同意學生與教授討論擬定專題研究的題目，在教授的個別指導下，進行實驗研究，並將研究結果寫成報告。",
    "schedule": "a. 週次    b. 單元主題\n1.    Introduction\n2.    Project Status Update & Work Assignments\n3.    Data Analysis & Literature Survey\n4.    Next Steps & Literature Survey\n5.    Proposal for Design Testing Equipment\n6.    Proposal for Design Testing Equipment (Refined)\n7.    Detail Design for Design Testing Equipment\n8.    Detail Design for Design Testing Equipment (Refined)\n9.    Midterm Group Report\n10.   Detail Design for Design Testing Equipment (Update)\n11.   Manufacturing the Testing Equipment\n12.   Status Update & Literature Survey\n13.   Status Update & Literature Survey\n14.   Data Collection & Literature Survey\n15.   Data Collection & Literature Survey\n16.   Status Update/Analysis & Literature Survey\n17.   Status Update/Analysis & Discussion\n18.   Final Report",
    "scorePolicy": "Final Report 100%",
    "materials": "教師 ppt",
    "consultation": "Email 聯絡",
    "remarks": "Email 聯絡",
    "foreignLanguageTextbooks": false
  },
  {
    "name": "黃晟豪",
    "email": "chhuang@stust.edu.tw",
    "latestUpdate": "2023-06-08 18:32:32",
    "objective": "先修課程：負責教授同意學生與教授討論擬定專題研究的題目，在教授的個別指導下，進行實驗研究，並將研究結果寫成報告。\nThe topic of the special projects is discussed and together by the students and advisor. Under the face-to -face instruction of the advisor the student will conduct the research and experiments, and the final report at the end of the semester.",
    "schedule": "第 1~6 週      文獻回顧並決定主題\n第 7~12 週    進行初步規劃與試驗\n第 13~18 週  完成初步測試並研擬改善方式",
    "scorePolicy": "參與度  30%\n完成度  30%\n驗證與實驗精神  30%\n其他 10%",
    "materials": "自編教材",
    "consultation": "與學生建立 LINE 群組",
    "remarks": "與學生建立 LINE 群組，遠距資訊將透過群組發布",
    "foreignLanguageTextbooks": false
  }
]
