[
  {
    "name": "李弘毅",
    "email": "hungyi1208@gmail.com",
    "latestUpdate": "2023-09-11 01:10:24",
    "objective": "本課程內容包括以下主題﹕各種冷凍空調用熱交換器之介紹、熱交換器熱傳與效率分析、熱交換器結垢問題分析及熱傳增強技術。",
    "schedule": "1 基礎流力及熱傳回顧\n2 熱交換器之分類及應用\n3 熱交換設計方法\n4 熱交換設計方法\n5 鰭片分析\n6 熱傳增強技術\n7 密集式熱交換器之熱傳及壓損\t\n8 密集式熱交換器之熱傳及壓損\n9 期中考\n10 鰭管式熱交換器之設計\n11 鰭管式熱交換器之設計\n12 鰭管式熱交換器之設計\n13 再生式熱交換器之設計\n14 再生式熱交換器之設計\n15 殼管式熱交換器之設計\n16 殼管式熱交換器之設計\n17 熱交換器結垢問題分析\n18 期末考",
    "scorePolicy": "作業及課程參與: 30%，期中考: 30%，期末考: 40%",
    "materials": "講義\n熱交換設計，王啟川，五南圖書出版公司，民國九十六年。",
    "consultation": "開學後建立冷凍空調熱交換器課程 Line 群組",
    "remarks": "因應學校二教整修工程施作，本 (112-1) 學期於第二教學大樓教室授課之課程，將配合總務處施工期程實施遠距教學至 9 月 28 日 (若有延長將另行公告) 。遠距教學相關事宜將使用 Microsoft Teams 進行。團隊連結：https://teams.microsoft.com/l/team/19%3atQvu5ntLvlNLtm9SMIHkfhuRjok8v--PH7PpBDzGh7g1%40thread.tacv2/conversations?groupId=494a8e53-e1d0-45e9-aa45-2641c7554566&tenantId=8d5a4e66-7a93-41fb-b7ac-2fdb9d7a0c7a 團隊代碼：utzy94j",
    "foreignLanguageTextbooks": false
  }
]
