[{"name":"李來春","email":"f10666@ntut.edu.tw","latestUpdate":"2008-02-19 11:33:27","objective":"因應國際分工、快速研發的需求，本課程以研究設計團隊如何有效地運用同步溝通媒介（如:Interwise, Skype），執行產品設計專案或設計競賽案，討論小組成員所提出的設計提案，同時善用網路資源，發揮團隊合作精神，完成設計專案的目標。本課程可藉由實際案例探討遠距設計的問題、最佳化的設計模式，以及學習到有效運用電腦中介工具與溝通的技能。","schedule":"1 緒論、課程介紹\n2 各端實驗環境與連線設定(Interwise, Skype)，連線品質與問題排除， Interwise 溝通平台介紹\\\n3 小組成員任務分派與分工合作，設計競賽的特性、得獎作品賞析、參與策略\n4 『設計競賽一/產學合作案』，針對主題進行資料蒐集\n5 資料分析與發展方向討論，設計問題定義與解決對策\n6-9 設計構想發展與修改\n10 實驗後心得分享與改善意見交流\n11 『設計競賽二』、針對主題進行資料蒐集與分析\n12 歷年得獎作品分析、設計問題定義與解決對策\n13-16 設計構想發展與修改\n17 實驗後心得分享與改善意見交流\n18 期末檢討與報告繳交\n","scorePolicy":"出席並參與討論40%\n設計報告 60%","materials":"　","foreignLanguageTextbooks":false}]
