[{"name":"鄭智成","email":"jcjeng@ntut.edu.tw","latestUpdate":"2008-02-18 15:52:28","objective":"此課程為化工程序的核心理論基礎，其內容探討熱量以及質量輸送之現象，以便應用於化工單元操作以及反應工程有關之計算與設計。","schedule":"1-2週 Fundamentals of Heat Transfer 熱傳遞學基本原理\n3週   Differential Equations of Heat Transfer 熱傳遞微分方程式\n4-5週 Steady-State Conduction 穩態熱傳導\n6-7週 Convective Heat transfer 熱對流\n8週   Convective Heat Transfer Correlations 熱對流傳遞關係式\n9週   Midterm Exam. 期中考\n10週  Radiation Heat Transfer 熱輻射\n11-12週 Fundamentals of Mass Transfer 質量傳遞之基本概念\n13週    Differential Equations of Mass Transfer 質量傳遞微分方程式\n14-15週 Steady-State Molecular Diffusion 穩態分子擴散\n16-17週 Convective Mass Transfer 質量對流傳遞\n18週    Final Exam. 期末考","scorePolicy":"期中考 35%\n期末考 35%\n作業與出席狀況 30%","materials":"教科書名: Fundamentals of Momentum, Heat and Mass Transfer\n作者: J. R. Welty et al.\n出版者: John Wiley &amp; Sons Company; 出版日期: 2000 Fourth Edition\n歐亞書局代理","foreignLanguageTextbooks":false}]
