[{"name":"安揚龍","email":"ylan@ntut.edu.tw","latestUpdate":"2015-02-01 18:16:38","objective":"介紹會計學之基本觀念， 會計循環 - 包括分錄、過帳、試算、結算及財務報表之編製。逐一說明財務報表各個項目，最後並介紹財務報表之分析。修畢本課程之後能瞭解會計學之基本原理，會計資料處理及財務報表產生之整個過程，以及簡單之財務報表分析技術，並為未來之企業及財務相關課程打下良好基礎。","schedule":"第一週   課程說明（大綱、評分標準、考試方式、期末報告規定）\n第二週   Ch.1 會計基本觀念\n第三週   Ch.2 會計科目與借貸法則\n第四週   Ch.3 平時會計處理程序\n第五週   Ch.4 期末處理程序─調整、結帳與編表\n第六週   Ch.5 帳簿組織\n第七週   Ch.6 會計與應負憑單制度\n第八週   Ch.7 買賣業會計\n第九週   期中考試週\n第十週   Ch.8 現金與內部控制\n第十一週 Ch.9  應收帳款\n第十二週 Ch.10 存貨\n第十三週 Ch.11 營業用資產\n第十四週 Ch.12 流動負債\n第十五週 Ch.13 合夥會計\n第十六週 Ch.14、Ch.15 公司會計\n第十七週 Ch.16 投資\n第十八週 期末考試週","scorePolicy":"平時10%\n期中40%\n期末50%","materials":"吳佳噏噏著    會計學   華泰出版","foreignLanguageTextbooks":false}]
