[{"name":"韓麗龍","email":"llhan@ntut.edu.tw","latestUpdate":"2015-02-08 15:22:22","objective":"材料科學簡介、原子與離子排列、原子與離子排列中的缺陷、材料內原子與離子的移動、凝固原理、機械性質、固溶體與相平衡、鋼鐵材料及其應用、非鐵合金、陶瓷材料","schedule":"第一週     第1章 材料科學與工程簡介\n第二週     第2章 原子結構\n第三週     第3章 原子與離子排列\n第四週     第4章 原子與離子排列中的缺陷\n第五週     第5章 材料內原子與離子的移動\n第六週     第6章 機械性質\n第七週     第7章 應變硬化與退火\n第八週     第8章 凝固原理\n第九週     期中考\n第十週     第9章 固溶體與相平衡\n第十一週   第10章 散步強化與共晶相圖\n第十二週   第11章 相變化與熱處理產生散步強化\n第十三週   第12章 鋼與鑄鐵之熱處理\n第十四週   第12章 鋼與鑄鐵之熱處理\n第十五週   第13章 非鐵合金\n第十六週   第13章 非鐵合金\n第十七週   第14章 陶瓷材料\n第十八週   期末考","scorePolicy":"(1)作業、小考及出席成績佔30%\n(2)期中考佔30%\n(3)期末考佔40%","materials":"教科書:\n材料科學與工程，第6版，譯者：蘇春𤂌、劉偉隆、…。\nISBN 978--986-6121-30-2\n2011年9月，歐亞書局\n(The Science and Engineering of Materials, Sixth Edition, Donald R. Askeland)\n\n參考書：\n材料科學概論（第五版），盧陽明 譯\nFoundations of Materials Science and Engineering, 5e, William F. Smith\nOffice：綜科館616-1","foreignLanguageTextbooks":false}]
