[{"name":"王玉瑞","email":"yrwang@ntut.edu.tw","latestUpdate":"2014-12-22 21:21:06","objective":"材料科學為工程教育的重要科技，材料的性質與特性，為現代工程設計中佔有相當重要的地位，金屬材料的各種性質，都基於其內部構造的變化，其內部原子聚集成規則的結晶構造，亦或聚集成非結晶構造，其所形成的各種物理特性，由最基本的結晶構造開始了解。電子顯微鏡，破壞力學，超導性，電傳導，超塑性，動態回復，動態時效應變。差排理論、結晶核的形成與成長，合金相理論，晶界自由度，鑄造物的成核與均質化，硬化現象，固體擴散現象，破壞現象及理論，潛變的形成與原因等，充分了解金屬材料特性上的理論基礎與變化軌跡。","schedule":"Week 1～２, Solid solutions\nWeek ３, Phases\nWeek ４～５, Binary phase Diagrams\nWeek ６～７, Diffusion in substitutional solid solutions\nWeek ８, Interstitial diffusion\nWeek 9, Midterm Exam\nWeek 10~12, Solidification of Metal\nWeek 13~14, Nucleation and Growth Kinetics\nWeek 15, Precipitation Hardening\nWeek 16~17 Deformation Twinning and Martensite Reactions\nWeek 18, Final Exam","scorePolicy":"1. 期中期末考各占４０％\n2. 出席率上課態度作業２０％","materials":"Physical Metallurgy Principles, 3rd Ed., Robert E. Reed-Hill, Reza Abbaschian","foreignLanguageTextbooks":false}]
