[
  {
    "name": "邵文政",
    "email": "wcshao@ntut.edu.tw",
    "latestUpdate": "2021-09-01 22:04:11",
    "objective": "為追求「永續發展與人本健康」之目的，使既有與新建的居住環境，配合我國「室內空氣品質管理法」規範下運作，提昇民眾居住環境健康品質效益，針對病態建築之環境問題，其涵蓋醫療、法律、建築、化學、生物等領域，綜合診斷以進行改善。本課程為第一階段之系列課程，其內容包括： 一。健康環境概念：說明何謂「病態建築」，探討室內空氣與健康之關係。 二。建築物污染源：探討來自各建築材料的化學物質逸散及其對人體健康之影響，並提出室內污染物質濃度減低對策。 三。生物性污染源：探討黴菌、蹣、白蟻及寵物等帶來的室內空氣污染。 四。診斷技術：說明室內空氣品質診斷方法及病態建築改善之專業技術，配合案例介紹探討新、舊建築物室內環境品質的設計預防、診斷改善技術。",
    "schedule": "週次  日期　　單元　　課程內容\n1         9/15        1-1         課程介紹\n2　　   9/22　　  1-2　　        病態建築概論\n3　　   9/29　　  1-3　　        IEQ 基準及研究方法\n4　　   10/6　　  1-4　　        IAQ 檢測 SOP 及儀器介紹\n5　　   10/13　　  1-5　　        健康環境概論 (一)\n6　　   10/20　　  1-6　　        健康環境概論 (二)\n7　　   10/27　　  1-7　　        建築物污染源 (一)\n8　　   11/3        1-8　　        建築物污染源 (二)\n9　　   11/10      1-9　　        專題演講 (A)\n10　　   11/17　　  1-10　　專題演講 (B)\n11　　   11/24　　  1-11       生物性污染源 (一)\n12　　   12/1  　　  1-12       生物性污染源 (二)\n13　　   12/8        1-13       診斷技術 (一)\n14　　   12/15      1-14       診斷技術 (二)\n15　　   12/12　　  1-15       期末報告 - 1\n16　　   12/29　　  1-16       期末報告 - 2\n17　　   1/5          1-17       期末報告 - 3 \n18　　   1/12   　　  1-18       學期總檢討",
    "scorePolicy": "1. 出席率規定：三次（含）以上未到課，學期總成績不及格（65 分）。\n 2. 學期總成績考核方式：[平時成績 40%＋期中翻譯報告 30%＋期末專題報告 30%]±5%\n3. 班級總平均上限：85 分。",
    "materials": "1. Sick House 一級診斷士教材 (上)\n2.&lt; 室內環境品質簡易自評手冊 & gt;/ 內政部建築研究所。\n3.&lt; 建築室內空氣品質管理機制之研究 & gt;/ 內政部建築研究所。\n4.&lt; 綠設計 健康住家指南 & gt; 艾倫˙柏曼 著 / 洪世民 譯 / 日月文化出版有限公司\n5.&lt; 設計自然屋 - 有機住宅實用指南 & gt; 大衛˙皮爾森 著 / 洪世民 譯 日月文化出版有限公司\n6.&lt;2011 綠建材解說與評估手冊更新版 & gt;/ 內政部建築研究所。\n7.&lt; 環境科學概論 & gt;\n8.&lt; 職業病概論 & gt;\n9. 室內空氣品質 (IAQ) 及室內環境品質 (IEQ) 相關研究、專書及政府出版品。\n10.LEED/WELL  Evaluation System",
    "foreignLanguageTextbooks": true,
    "covid19": {
      "lv2Description": null,
      "courseScoreMethod": "均採線上報告",
      "courseInfo": "https://teams.microsoft.com/l/channel/19%3aDTrYQNxWFXgXDOXOe9pfOtZ-9nnL2nsFqvGIqKkFrqk1%40thread.tacv2/%25E4%25B8%2580%25E8%2588%25AC?groupId=9fb048d2-20e9-481a-9fc6-21a8f523d5ee&amp;tenantId=dfb5e216-2b8a-4b32-b1cb-e786a1095218",
      "courseURL": "https://teams.microsoft.com/l/channel/19%3aDTrYQNxWFXgXDOXOe9pfOtZ-9nnL2nsFqvGIqKkFrqk1%40thread.tacv2/%25E4%25B8%2580%25E8%2588%25AC?groupId=9fb048d2-20e9-481a-9fc6-21a8f523d5ee&amp;tenantId=dfb5e216-2b8a-4b32-b1cb-e786a1095218",
      "contactInfo": "健康環境研究室 / 設計館 253 / 分機 2988\n邵文政研究室 / 設計館 551-3 / 分機 2903",
      "additionalInfo": "可經洽研究生課程 TA 或助教詢問相關修課事宜",
      "lv2Method": "遠距上課"
    }
  }
]
