[
  {
    "name": "方志鵬",
    "email": "jpfang7742@gmail.com",
    "latestUpdate": "2021-09-14 10:52:22",
    "objective": "(1) Arduino 開發環境簡介 (2) 數位 I/O 控制 (3) 類比 I/O 控制 (4) 鍵盤掃描與七段顯示器 (5) 聲音播放 (6) RGB LED (7) LCD (8) 中斷 (9) 綜合應用。",
    "schedule": "第 1 週 課程簡介與開發環境介紹\n第 2/3 週 數位 I/O 控制與模擬程式\n第 4/5 週 類比 I/O 控制與模擬程式\n第 6/7 週 鍵盤掃描與模擬程式\n第 8/9 週 七段顯示器與模擬程式\n第 10 週聲音播放與模擬程式\n第 11/12RGB LED 與模擬程式\n第 13 週 LCD 與模擬程式\n第 14 週 中斷與模擬程式\n第 15/16/17/18 週 期末專題",
    "scorePolicy": "師生互動 10%\n實習成果 70%\n期末專題 20%",
    "materials": "Arduino 全能微處理機實習 強效解析 第 4 版 艾迪諾 編著 全華\nTinkerCAD 自編講義",
    "foreignLanguageTextbooks": false,
    "covid19": {
      "lv2Description": null,
      "courseScoreMethod": "非放假的上課日，每周上傳實習的模擬內容及結果作為實習成果的成績；期末報告在最後一周上課的結束前上傳，實習報告中包括模擬內容、結果、及問題討論。",
      "courseInfo": null,
      "lv2Method": "遠距上課"
    }
  }
]
