[
  {
    "name": "蔡福裕",
    "email": "fuyutsai@ntut.edu.tw",
    "latestUpdate": "2021-09-29 16:32:28",
    "objective": "本門授課之目的在介紹各種有機化合物之合成方法、原理及應用，並探討有機實驗室常用之有機反應及其反應機構。",
    "schedule": "1-3 週: Organic Synthesis\n4-8 週: Nucleophilic Addition to Polar pi Bonds\n第 9 週：期中考\n10-13 週: Nucleophilic Addition-Elimination Reaction\n14-17 週: Aromatic Substitution \n第 18 週：期末考",
    "scorePolicy": "期中考 50%\n期末考 50%",
    "materials": "Organic Chemistry\nJoel Karty\n2nd Edition",
    "foreignLanguageTextbooks": true,
    "covid19": {
      "lv2Description": "開學第一週採遠距教學\n第二週起實體授課 ",
      "courseScoreMethod": "採實體紙筆測驗為主，若無法實體紙筆測驗則改採線上開書紙筆測驗",
      "courseInfo": "第一週依照課表時間 Google meet 遠距教學\n教材提供於北科 i 學園 PLUS",
      "courseURL": "meet.google.com/pdu-oifg-epj",
      "contactInfo": "分機 2437 或 2425\n分子館 4F 辦公室或 402 室",
      "additionalInfo": null,
      "lv2Method": "分流上課"
    }
  }
]
