[{"name":"鄭怡雯","email":"ywcheng@ntut.edu.tw","latestUpdate":"2021-06-05 18:21:07","objective":"本課程包括攝影創作、地方導覽、視覺社會學與策展實務等四個部分，旨在透過理論與實作的多元跨域結合，開啟學生對於攝影創作的社會性思考，以及探索如何以攝影作為社會實踐的一種方式，並於期末進行公開展演。\nThis course mainly includes four parts: photography creation, local tour, visual sociology and curating practice. Based on interdisciplinary theories and practices, it is aimed to inspire student how to employ the sociological thinking in photography and explore social practices through photography projects.  In the end of the semester, students are required to exhibit the final works and develop dialogues with the public.","schedule":"第1週　　課程介紹\n第2週　　進入場域之前—認識地方產業與勞動文化記憶遺產\n第3週　　田野調查與口述歷史訪談方法介紹\n第4週　　環境肖像怎麼拍?  \n第5週　　實踐場域導覽與拍攝實作 (1)  \n第6週　　實踐場域導覽與拍攝實作 (2)  \n第7週　　第一階段攝影教學與評圖\n第8週　　攝影創作與社會實踐相關計畫介紹與討論\n第9週　　期中考周\n第10週　　從物件再出發—在技術物中體會STS\n第11週　　再訪實踐場域與拍攝—挖掘物件秘密 (1)\n第12週　　再訪實踐場域與拍攝—挖掘物件秘密 (2)\n第13週　　第二階段攝影教學與評圖\n第14週　　分組作品討論 (1)\n第15週　　分組作品討論 (2)\n第16週　　策展實務工作坊\n第17週　　佈展\n第18週　　公開展演與導覽","scorePolicy":"個人作業  25%\n期中作業  25%\n期末成果演展 50%","materials":"教師自編","foreignLanguageTextbooks":false}]
