[{"name":"曾世杰","email":"sjtzeng@ntut.edu.tw","latestUpdate":"2009-02-18 10:08:29","objective":"本校之普通物理課程專為工程科系背景之同學設計，主要的目的是鼓勵同學參與大自然運行奧秘、法則之探索，並供給爾後修習專業課程之堅實基礎。本課程之內容包含力學、熱力學、聲學、電磁學、光學及近代物理。教授者可按每週三小時、二個學期的時間設計、再參酌各系不同之需求、加強或節略某些章節。","schedule":"1.Coulomb'slaw 2.Finding the electric field I 3. Finding the electric field II 4.Finding the electric potential 5.Capacitor and capacitance,Ohm's law 6.Circuit theory, Magnetic force 7.Magnetic force 8.Current-produced Magnetic fields 9.Current-produced Magnetic fields 10.Inductance 11.Alternating fields and current 12.Maxwell'sequations,Models of magnetism 13.Nature of electromagnetic waves 14.Geometric optics 15. Optical interference and diffraction","scorePolicy":"平時考，期中考，期末考","materials":"　","foreignLanguageTextbooks":false}]
