[{"name":"王長春","email":"ccwang.t123@msa.hinet.net","latestUpdate":"2009-02-13 22:18:14","objective":"本門課藉由濕空氣線圖討論空氣調節之過程，分析人體舒適與空氣品質之需求，及各種空調設備系統之設計。本門課在空調負荷計算原理與方法涵蓋輻射熱、熱傳導及熱儲存效應等之分析，系統設計包括送風與送水系統之計算與設計，及室內送風分佈之理論與設計。","schedule":"(1) 課程介紹/導論.(2)空調系統/濕空氣性質.(3)各種空調處理過程.(4)室內環境品質.(5)建築構組件內熱傳遞.(6)太陽輻射.(7)暖房負荷.(8)冷房負荷.(9)期中考.(10)冷房負荷.(11)能源估算.(12)流動泵及管路設計.(13)流動泵及管路設計.(14)空間空氣擴散.(15)風扇及建築物內空氣分配.(16)風扇及建築物內空氣分配.(17)直接接觸熱質傳遞.(18)期末考.","scorePolicy":"(1)作業40%.(2)期中考20%.(3)期末考20%.(4)出席率20%.","materials":"1. 教科書: 空調工程與設計  黃瑞隆等五位編譯   高立圖書公司\n2. 參考書:(1)Principle of heating Ventilating and Air-Conditioning   \n             by Ronald H. Howell \n          (2)Modern Heating &amp;Ventilating System Design by Geroge E. \n             Clifford","foreignLanguageTextbooks":false}]
