[
  {
    "name": "張正春",
    "email": "ccchang@ntut.edu.tw",
    "latestUpdate": "2021-12-29 18:36:18",
    "objective": "1. 訓練學生有基本的 Python 程式設計能力\n2. 訓練學生有能力用電腦解決問題\n3. 訓練學生有能力看懂他人寫的程式\n\n1. Basic Python programming\n2. Problem solving through computer programming\n3. Understand programs coded by the third party.",
    "schedule": "第一週 認識 Python：下載、安裝 Python 及開發環境介紹；\nPython 的輸入 print () 與輸出 input ()。\n第二週 控制敘述 (一)：if else, switch；\nPython 的基本資料類型：int, float, bool, …。\n第三週 控制敘述 (二)：for\n第四週 複習\n第五週 控制敘述 (三)：while, do while\n第六週 複習\n第七週 資料儲存容器：tuple, list, dict, set (一)。\n第八週 資料儲存容器：tuple, list, dict, set (二)。\n第九週 期中考\n第十週 函式使用 (一)\n第十一週 函式使用 (二)\n第十二週 第三方函式庫\n (讓同學感受協力廠商的模組套件)\n第十三週 陣列的處理 (一)\n第十四週 陣列的處理 (二)\n第十五週 資料夾與檔案\n第十六週 Python 實務應用\n (介紹實務應用讓同學感受爬蟲、Google 地圖… 等實務應用)\n第十七週 複習\n第十八週 期末考",
    "scorePolicy": "作業 40%,   期中考  30%,   期末考  30%",
    "materials": "黃建庭，《Python 程式設計：從入門到進階應用 (第三版)》，2020。\n出版社：「全華圖書股份有限公司」\nISBN：9789865033248",
    "foreignLanguageTextbooks": false
  }
]
