[{"name":"楊哲化","email":"chyang@ntut.edu.tw","latestUpdate":"2020-01-15 10:05:12","objective":"先修課程：負責教授同意。1.基礎物理光學2.超音波簡介3.雷射超音波的生成4.雷射超音波的偵測5.刀邊緣技術6.雙頻干涉儀7.費里裴洛干涉儀8.非線性晶體干涉儀9.雷射超音波技術於非破壞檢測之應用10.雷射超音波技術於材料性質量測之應用11.雷射超音波技術發展的未來趨勢\n1.Introduction to physical optics, 2.Introduction to ultrasonic waves, 3.Optical generation of ultrasound waves, 4.Detection of ultrasonic waves with optical methods, 5.Knife edge technique, 6.Hetrodyne interferometers in LUT, 7.Fabry-Perot interferometers, 8.Two-way mixing interferometers, 9.Application of LUT in nondestructive testing, 10.Application of LUT to material characterizations, 11.Future trend of LUT.","schedule":"Week　　Date　　Contents\n1　　2/17　　Course introduction\n2　　2/24　　National holiday\n3　　3/2　　Introduction to laser ultrasonics\n4　　3/9　　Principle of ultrasonics\n5　　3/16　　Lasers\n6　　3/23　　Physical optics\n7　　3/30　　Generation of ultrasound with optical methods (1)\n8　　4/6　　Generation of ultrasound with optical methods (2)\n9　　4/13　　Measurement of ultrasound signals\n10　　4/20　　Midterm Exam\n11　　4/27　　Knife edge technique\n12　　5/4　　Lab on knife edge technique\n13　　5/11　　Michaelson interferometers\n14　　5/18　　Fabry-Perot Interferometers\n15　　5/25　　Tow-way mixing interferometers\n16　　6/1　　LUT in industrial applications\n17　　6/8　　Project presentation\n18　　6/15　　Final Exam","scorePolicy":"Final: 40%, Midterm: 30%, Project: 30%","materials":"C.B Scruby and L.E Drain, Laser Ultrasonics Techniques and Applications, CRC Press","foreignLanguageTextbooks":true}]
