[{"name":"陳匡正","email":"kchen34@gmail.com","latestUpdate":"2020-02-14 02:30:47","objective":"本課程將可增進學生撰寫不同種法律文件之能力，包含律師函與其回覆、契約、內部備忘錄及信件。本課程將包括法律寫作的基礎、格式與範例、撰寫與修訂的練習、同儕審查、講授者進一步的回覆。在此課程結束以後，學生經由不同種指定作業所完成的各類型文件，將可大幅度地改善其寫作技巧。","schedule":"第一週 (109/3/2~109/3/7) 課程導論；美國法律制度介紹(I)\n第二週 (109/3/9~109/3/14) 美國法律制度介紹(II)\n第三週 (109/3/16~109/3/21) Feist Publications v. Rural Telephone Service案探討\n第四週 (109/3/23~109/3/28) Kirtsaeng v. John Wiley &amp; Sons, Inc.案探討 　　\n第五週 (109/3/30~109/4/4) 兒童節補假一天\n第六週 (109/4/6~109/4/11) Campbell v. Acuff-Rose Music, Inc.案探討；繳交Kirtsaeng v. John Wiley &amp; Sons, Inc.案例摘要\n第七週 (109/4/13~109/4/18) Ty, Inc. v. GMA Accessories, Inc.案探討\n第八週 (109/4/20~109/4/25) Naruto v. Slater案探討\n第九週 (109/4/27~109/5/2) 作為「109學年度四技二專及二技統一入學測驗」之考場停課一次\n第十週 (109/5/4~109/5/9) Diamond v. Chakrabarty案探討；繳交Naruto v. Slater案例摘要\n第十一週 (109/5/11~109/5/16) Graham v. John Deere Co.案探討\n第十二週 (109/5/18~109/5/23) Alice Corp. v. CLS Bank International案探討\n第十三週 (109/5/25~109/5/30) AMP v. Myriad Genetics, Inc.案探討\n第十四週 (109/6/1~109/6/6) J.E.M.Ag. Supply, Inc. v. Pioneer Hi-Bred International, Inc.案探討；繳交AMP v. Myriad Genetics, Inc.案例摘要\n第十五週 (109/6/8~109/6/13) Impression Products, Inc. v. Lexmark International, Inc.案探討\n第十六週 (109/6/15~109/6/20) TrafFix Devices, Inc. v. Marketing Displays, Inc.案探討\n第十七週 (109/6/22~109/6/27) 端午節調整放假一天\n第十八週 (109/6/29~109/7/4) Big O Tire Dealers, Inc. v. The Goodyear Tire &amp; Rubber Company案探討","scorePolicy":"1.課後作業(三份) 30%\n2.上課出席 30%\n3.法律英文判決上台報告、課堂參與及表現 40%","materials":"1.課程講義(美國法院判決)。\n2.王澤鑑主編，英美法導論，元照出版有限公司，2010年7月。\n3.潘維大著，黃陽壽譯，英美契約法案例解析(一)(二)，瑞興圖書股份有限公司，1997年9月。\n4.潘維大著，英美侵權行為法案例解析(上)(中)(下)，瑞興圖書股份有限公司，2013年4月。\n5.Alan L. Dworsky著，馮震宇審訂，江崇源、 林懿萱譯，法律英文寫作的第一本書，元照出版公司，2004年11月。\n6.何主宇著，法律英文讀寫實務，寂天文化事業股份有限公司，2004年7月。\n7.張冠群著，基礎法學英文，元照出版有限公司，2014年10月。\n8.徐慧怡、張心悌等著，法學英文，元照出版有限公司，2015年3月。","foreignLanguageTextbooks":true}]
