[{"name":"張合","email":"f10381@ntut.edu.tw","latestUpdate":"2016-02-26 15:27:43","objective":"專題報告、專題演講、機械與製造科技相關產業介紹與討論、研究小組討論","schedule":"1.介紹課程內容與評分方式\n2.射頻元件技術發展與市場\n3.可攜式、植入性醫療產品技術開發與商品化認證\n4.創新與風險管理 \n5.生物分子感測元件\n6.自然語言處理的挑戰\n7.量子點與綠能科技之發展\n8.台灣軌道運輸之發展\n9.造物教育的推動\n10.科技藝術與機電整合\n11.台北藝術大學藝術與科技中心\n12.馬達科技及應用\n13.Innovation, Technology,  Project Management, and Career Planning\n14.微細加工新技術\n15.微機電系統\n16.待定\n17.A New Algorithm for Reliability-Based Design Optimization with Arbitrarily Distributed Uncertainties","scorePolicy":"1 課堂表現 50%\n2 心得報告 50%, 不允許補交報告\n3 缺課三次即重修,無法上課需事先請假\n4 遲到10分鐘以上累計3次視為一次缺課\n5 代替簽到或代寫心得報告者,當事人及代替者皆重修\n6 每週三下午公告缺課名單","materials":"每週邀請不同領域專家做專題演講","foreignLanguageTextbooks":false}]
