[{"name":"孫郁琪","email":"ycsun@ntut.edu.tw","latestUpdate":"2014-02-13 15:55:06","objective":"This course introduces a general framework for English language course design to be applied in varying contexts and circumstances. Students are required to develop a course of their own through which they will learn to become aware of decision making at each stage of the course design and to elaborate and justify their design. They are also expected to integrate critical theories in education into their course design by examining the viewpoints of various classroom teachers and researchers.","schedule":"Week 1     Introduction\nWeek 2     Chapters 1 &amp; 2\nWeek 3     Chapters 3 &amp; 4\nWeek 4     Chapters 5 &amp; 6\nWeek 5     Chapters 7 &amp; 8\nWeek 6     Chapters 9 &amp; 10\nWeek 7     No Class!\nWeek 8     Final Project Meeting I\nWeek 9     Final Project Meeting II\nWeek 10    SR 1 \nWeek 11    SR 2 \nWeek 12    SR 3 \nWeek 13    SR 4 \nWeek 14    SR 5 \nWeek 15    SR 6 \nWeek 16    Final Project Evaluation I\nWeek 17    Final Project Evaluation II\nWeek 18    Final Project Due","scorePolicy":"Class Participation: 40%\nGroup Presentations: 30%\nFinal Project: 30%","materials":"　","foreignLanguageTextbooks":false}]
