[{"name":"鍾仁傑","email":"crj@crj.cc","latestUpdate":"2018-07-04 23:31:27","objective":"大學入門與工程倫理是針對大一新生所開授之全校性課程。用以協助學生:(一)認識高等教育的理念、目的與價值(二)有效學習(三)涵養正視困境並妥適因應能力。藉以實踐自我鍛鍊，自我掌握，自我經營並建構宏觀視界的高等教育宗旨。","schedule":"拜師禮暨校長演講\n\n課程導論暨大學教育理念及價值\n情緒管理與壓力處理\n各院系介紹\n各院系介紹\n教師自選主題\n做自己的圓夢大使\n北科校史館暨圖書館資料庫指引\n教師自選主題\n校友典範的學習與傳承\n工程倫理1*\n教師自選主題\n工程倫理2*\n成為人見人愛的溝通高手\n校友典範的學習與傳承\n教師自選主題\n工程倫理3*\n兩性關係\n\n綠建築與永續校園\n期末回饋","scorePolicy":"學習評量方式\n平常成績（出席、討論、學習態度）：40％\n點名一次沒到扣總分十分\n\n學習單, 演講心得報告：35％\n\n單元作業：25％\n分組作業\n個人聽講報告","materials":"講義 (北科i學園)\n影片\n指定閱讀書籍及推薦書目","foreignLanguageTextbooks":false}]
