[{"name":"李立緯","email":"011708good@gmail.com","latestUpdate":"2018-07-01 13:31:30","objective":"生命科學是以科學的角度探討生命各層面特徵的綜合知識,與我們現在未來息息相關。地球上存在各式各樣的生命，可由單一細胞(基本的生命單元)所構成，再發展成各種不同的生物體，演化成多樣性的生物物種。對人類而言，終其一生都與週遭的物種密切相關，例如營養的攝取，疾病的發生與治療，藥物的發明, 環境的汙染與保護等都屬於生命科學的一環，是大學生應該具備的基本知識。","schedule":"第1週　　緒論: 什麼是生命科學\n第2週　　生命的起源　　\n第3週　　遺傳學\n第4週　　分子生物學\n第5週　　生物的化學組成 ,有機化合物與生物大分子　　\n第6週　　細胞 生命的基本單位    \n第7週　　動物生理學                     \n第8週　　孼疫學與疾病                   　　\n第9週　　期中考週\n第10週　　細菌學與疾病　　\n第11週　　病毒學與疾病\n第12週　　生物技術　　\n第13週   　　環境學\n第14週　　生物倫理學　　\n第15週　　分組報告　　\n第16週　　分組報告\n第17週　　分組報告\n第18週　　期末考週","scorePolicy":"平時（出席，學習態度，討論）: 20%\n考試(期中與期末考): 60%\n分組報告: 20%","materials":"基礎生命科學，第二版，吳慶余 編著，藝軒圖書出版社\n生命科學概論 Introduction to life science， 總校閱： 張峻維、施養佳、張小娟， 新文京開發出版股份有限公司\n參考書籍：【請遵守智慧財產權，不得非法影印】","foreignLanguageTextbooks":false}]
