[{"name":"蔡偉和","email":"whtsai@ntut.edu.tw","latestUpdate":"2018-09-05 09:52:55","objective":"本課程介紹影視、廣播、與流行音樂產業之實務相關技術，著重於基本概念的應用。課程採用「問題導向學習」(Problem-based Learning, PBL)模式，除理論介紹外，亦藉由資料整理、分組討論、實地參訪、實作練習、與成果觀摩及報告等方式，激發學生之創造與創新能力。","schedule":"第1週　　影視技術概述\n第2週　　影視技術概述\n第3週　　影視產業實務\n第4週　　影視公司參訪\n第5週　　廣播技術概述\n第6週　　廣播技術概述\n第7週　　廣播產業實務\n第8週　　廣播公司參訪\n第9週　　流行音樂技術概述\n第10週　　流行音樂技術概述\n第11週　　流行音樂產業實務\n第12週　　唱片公司參訪\n第13週　　KTV公司參訪\n第14週　　問題與創意發想討論\n第15週　　問題與創意發想討論\n第16週　　實作成果觀摩與報告\n第17週　　實作成果觀摩與報告\n第18週　　期末考\n(實際進度將視同學學習情況微調)","scorePolicy":"參與情形 30%\n實作成果與報告 40%\n期末考 30%","materials":"自編教材","foreignLanguageTextbooks":false}]
