[{"name":"杜祖雯","email":"davinb@gmail.com","latestUpdate":"2011-09-13 01:02:19","objective":"1.介紹各類新興互動媒體科技在展示或行銷活動上的應用\n\n2.案例介紹及討論目前已知的技術及應用方式。\n\n3.跨媒體整合的專案規劃習作: 專案的規劃流程，需顧及的層面   \n   及問題， 內容發展方法\n\n4.著重互動媒體科技創意應用的啟發\n\n(10月或11月可能視授課情形安排校外參觀或演講)","schedule":"自第二週起隔週上, 上課時間及進度如下\n9/13   AB    課程概要與修課說明\n9/20   AB    互動媒體及展示或行銷活動應用基本概念、常用技術介紹\nCD     案例介紹與探討：博物館或博覽會\n10/4   AB    案例介紹與探討：商業活動或廣告\nCD     案例介紹與探討：店頭行銷或展示\n10/18 AB    案例介紹與探討：手機或網路行銷活動或綜合\nCD    互動媒體及展示或行銷活動相關規劃\n11/1   AB    學期專題主題構想提出及探討\nCD    資料收集與分析方法, 擬訂應用方向\n11/8            期中考  不上課\n11/22 AB    資料收集與分析及主題構想報告(期中報告)\nCD    互動創意應用探討\n12/6   AB    學期專題互動創意及應用方式提出及探討\nCD    視覺及表現方式, 技術應用探討\n12/20 AB    學期專題視覺及表現方式, 技術應用構想提出及探討\nCD    學期專題整合討論\n1/3     AB    期末專題發表\n1/10           期末考  不上課","scorePolicy":"平時表現  30%,   期中發表30%,  期末發表30%,  個人報告10%","materials":"自編教材","foreignLanguageTextbooks":false}]
